LICENSE
MANIFEST.in
README.rst
setup.py
django_primate.egg-info/PKG-INFO
django_primate.egg-info/SOURCES.txt
django_primate.egg-info/dependency_links.txt
django_primate.egg-info/not-zip-safe
django_primate.egg-info/top_level.txt
primate/__init__.py
primate/admin.py
primate/models.py
primate/auth/__init__.py
primate/auth/base.py
primate/auth/forms.py
primate/auth/helpers.py
primate/auth/mixins.py
primate/auth/models.py